.gitignore
README.md
customize.py
pyproject.toml
requirements.txt
setup.cfg
setup.py
.github/workflows/CI.template
.github/workflows/CI.yml
.github/workflows/publish.yml
nsgptorch/__init__.py
nsgptorch/_version.py
nsgptorch.egg-info/PKG-INFO
nsgptorch.egg-info/SOURCES.txt
nsgptorch.egg-info/dependency_links.txt
nsgptorch.egg-info/requires.txt
nsgptorch.egg-info/top_level.txt
nsgptorch/kernels/__init__.py
nsgptorch/kernels/distance.py
nsgptorch/kernels/nsrbf.py
nsgptorch/kernels/rbf.py
nsgptorch/kernels/transforms.py
nsgptorch/models/__init__.py
nsgptorch/models/gp.py
tests/__init__.py
tests/test_gpytorch.py