Metadata-Version: 2.1
Name: nsgptorch
Version: 0.1.2
Summary: Non-stationary GP package written from scratch in PyTorch
Home-page: https://github.com/patel-zeel/nsgptorch
Author: Zeel B Patel
Author-email: patel_zeel@iitgn.ac.in
License: MIT
Platform: UNKNOWN
Requires-Python: >=3.6
